np_upload_validation/__init__.py
np_upload_validation/exceptions.py
np_upload_validation/hpc.py
np_upload_validation/local.py
np_upload_validation/models.py
np_upload_validation/npc.py
np_upload_validation/py.typed
np_upload_validation/utils.py
np_upload_validation/validation.py
np_upload_validation/scripts/main.py
np_upload_validation-0.1.35.dist-info/LICENSE
np_upload_validation-0.1.35.dist-info/METADATA
np_upload_validation-0.1.35.dist-info/WHEEL
np_upload_validation-0.1.35.dist-info/entry_points.txt
np_upload_validation-0.1.35.dist-info/top_level.txt
np_upload_validation-0.1.35.dist-info/RECORD
