Metadata-Version: 2.1
Name: np-upload-validation
Version: 0.1.35
Summary: AWS upload validation
Author-email: Christopher Mochizuki <chrism@alleninstitute.org>
License: MIT
Project-URL: Repository, https://github.com/AllenInstitute/np-upload-validation
Project-URL: Issues, https://github.com/AllenInstitute/np-upload-validation/issues
Classifier: Development Status :: 3 - Alpha
Classifier: Programming Language :: Python :: 3
Classifier: Programming Language :: Python :: 3.9
Classifier: Programming Language :: Python :: 3.10
Classifier: Programming Language :: Python :: 3.11
Classifier: License :: OSI Approved :: MIT License
Classifier: Operating System :: Microsoft :: Windows
Classifier: Operating System :: POSIX :: Linux
Requires-Python: >=3.9
License-File: LICENSE
Requires-Dist: pydantic>=2.6.1
Requires-Dist: fabric>=3.2.2
Requires-Dist: numpy>=1.26.4
Requires-Dist: click>=8.1.7
Requires-Dist: python-dotenv>=1.0.1
Requires-Dist: zarr<2.18.1
Requires-Dist: wavpack-numcodecs>=0.1.5
Requires-Dist: npc-lims==0.1.185
Provides-Extra: np
